{
  "settimane": [
    {
      "id": "2026-W23",
      "confermato": true,
      "dal": "2026-06-01",
      "al": "2026-06-07"
    },
    {
      "id": "2026-W24",
      "confermato": true,
      "dal": "2026-06-08",
      "al": "2026-06-14"
    }
    ,{
      "id": "2026-W25",
      "confermato": true,
      "dal": "2026-06-15",
      "al": "2026-06-21"
    }
    ,{
      "id": "2026-W26",
      "confermato": true,
      "dal": "2026-06-22",
      "al": "2026-06-28"
    }
    ,{
      "id": "2026-W27",
      "confermato": true,
      "dal": "2026-06-29",
      "al": "2026-07-05"
    }
  ]
}
